README.md
setup.py
duspider/__init__.py
duspider/base.py
duspider/exceptions.py
duspider/medlive_login.py
duspider/tools.py
duspider.egg-info/PKG-INFO
duspider.egg-info/SOURCES.txt
duspider.egg-info/dependency_links.txt
duspider.egg-info/requires.txt
duspider.egg-info/top_level.txt
duspider/diseases/__init__.py
duspider/diseases/askbob.py
duspider/diseases/baidu.py
duspider/diseases/dayi_org.py
duspider/diseases/dxy.py
duspider/diseases/jbk39.py
duspider/diseases/orpha.py
duspider/diseases/xywy.py
duspider/drugs/__init__.py
duspider/drugs/askbob.py
duspider/drugs/drugbank.py
duspider/drugs/medlive.py
duspider/drugs/medscape.py
duspider/drugs/nmpa_gov.py
duspider/fund/__init__.py
duspider/fund/citexs.py
duspider/fund/kyzs.py
duspider/fund/nsfc.py
duspider/guide/__init__.py
duspider/guide/medlive.py
duspider/hosp/__init__.py
duspider/hosp/ahosp.py
duspider/hosp/haodf.py
duspider/hosp/xywy.py
duspider/hosp/yyk99.py
duspider/protein/__init__.py
duspider/protein/uniprot.py