Metadata-Version: 2.1
Name: duspider
Version: 0.0.14
Summary: Commonly used spiders
Author: DYZ
Author-email: duyuchau@gmail.com
Maintainer: DYZ
Maintainer-email: duyuchau@gmail.com
License: MIT
Platform: all
